aigcfile/clis/click/cli.py
aigcfile/clis/click/commands/rename.py
aigcfile/clis/click/commands/write.py
aigcfile/clis/click/utils/datatype.py
aigcfile/image/rename.py
aigcfile/image/rename_test.py
aigcfile/module/rename.py
aigcfile/module/write.py
aigcfile/text/write.py
aigcfile/text/write_test.py
aigcfile/utils/__init__.py
aigcfile/utils/check.py
aigcfile/utils/copy.py
aigcfile/utils/glob.py
aigcfile/utils/statistic.py
aigcfile/utils/suffix.py
aigcfile-0.0.3.dist-info/LICENSE
aigcfile-0.0.3.dist-info/METADATA
aigcfile-0.0.3.dist-info/WHEEL
aigcfile-0.0.3.dist-info/entry_points.txt
aigcfile-0.0.3.dist-info/top_level.txt
aigcfile-0.0.3.dist-info/RECORD
