Metadata-Version: 2.1
Name: aigcfile
Version: 0.0.3
Summary: File renaming, path acquisition, folder creation, file indexing and other operations.
Author-email: weiwenying <weiwenying520@gmail.com>
Project-URL: Homepage, https://gitlab.com/nuvic/2024/aigcfile
Project-URL: Issues, https://gitlab.com/nuvic/2024/aigcfile/-/issues
Classifier: Programming Language :: Python :: 3
Classifier: License :: OSI Approved :: MIT License
Classifier: Operating System :: OS Independent
Requires-Python: >=3.8
License-File: LICENSE
Requires-Dist: opencv-python
Requires-Dist: tqdm
Requires-Dist: click
